odoo/addons/product_medical/README.rst
odoo/addons/product_medical/__init__.py
odoo/addons/product_medical/__manifest__.py
odoo/addons/product_medical/data/in_vitro_diagnostic_data.xml
odoo/addons/product_medical/data/medical_data.xml
odoo/addons/product_medical/data/medicine_category_data.xml
odoo/addons/product_medical/data/ppe_category_data.xml
odoo/addons/product_medical/i18n/ca.po
odoo/addons/product_medical/i18n/de.po
odoo/addons/product_medical/i18n/es.po
odoo/addons/product_medical/i18n/product_medical.pot
odoo/addons/product_medical/migrations/13.0.1.1.0/post-migration.py
odoo/addons/product_medical/models/__init__.py
odoo/addons/product_medical/models/in_vitro_diagnostic.py
odoo/addons/product_medical/models/medical_category.py
odoo/addons/product_medical/models/medical_class.py
odoo/addons/product_medical/models/ppe_category.py
odoo/addons/product_medical/models/product_template.py
odoo/addons/product_medical/readme/CONTRIBUTORS.rst
odoo/addons/product_medical/readme/CREDITS.rst
odoo/addons/product_medical/readme/DESCRIPTION.rst
odoo/addons/product_medical/security/ir.model.access.csv
odoo/addons/product_medical/static/description/icon.png
odoo/addons/product_medical/static/description/index.html
odoo/addons/product_medical/views/in_vitro_diagnostic.xml
odoo/addons/product_medical/views/medical_class.xml
odoo/addons/product_medical/views/medicine_category.xml
odoo/addons/product_medical/views/ppe_category.xml
odoo/addons/product_medical/views/product_template.xml
odoo14_addon_product_medical-14.0.1.0.1.dist-info/METADATA
odoo14_addon_product_medical-14.0.1.0.1.dist-info/WHEEL
odoo14_addon_product_medical-14.0.1.0.1.dist-info/top_level.txt
odoo14_addon_product_medical-14.0.1.0.1.dist-info/RECORD
