Metadata-Version: 2.1
Name: odoo14-addon-product-medical
Version: 14.0.1.0.1
Summary: Base structure to handle medical products
Home-page: https://github.com/OCA/product-attribute
Author: Camptocamp, Odoo Community Association (OCA)
Author-email: support@odoo-community.org
License: AGPL-3
Platform: UNKNOWN
Classifier: Programming Language :: Python
Classifier: Framework :: Odoo
Classifier: License :: OSI Approved :: GNU Affero General Public License v3
Requires-Python: >=3.6
Requires-Dist: odoo (<14.1dev,>=14.0a)
